bed_reader-1.0.6.dist-info/METADATA
bed_reader-1.0.6.dist-info/WHEEL
bed_reader-1.0.6.dist-info/licenses/LICENSE.md
bed_reader-1.0.6.dist-info/licenses/AUTHORS.txt
bed_reader/tests/registry.txt
bed_reader/tests/test_opt_dep.py
bed_reader/tests/data/toydata.5chrom.bim
bed_reader/tests/data/small.mib
bed_reader/tests/data/toydata.5chrom.fam
bed_reader/tests/data/small_no_fam.bim
bed_reader/tests/data/500x400_o640_array.memmap
bed_reader/tests/data/small_too_short.bed
bed_reader/tests/data/small.deb
bed_reader/tests/data/small_too_short.fam
bed_reader/tests/data/small.maf
bed_reader/tests/data/small.fam_bad
bed_reader/tests/data/small.bim_bad_positions.bim
bed_reader/tests/data/some_missing.bed
bed_reader/tests/data/small.bim
bed_reader/tests/data/some_missing.val.npy
bed_reader/tests/data/small_too_short.bim
bed_reader/tests/data/sparse.fam
bed_reader/tests/data/badfile.bed
bed_reader/tests/data/small2_array.memmap
bed_reader/tests/data/smallmode0.fam
bed_reader/tests/data/smallmode0.bim
bed_reader/tests/data/plink_sim_10s_100v_10pmiss.fam
bed_reader/tests/data/small.fam
bed_reader/tests/data/small.bad_bim
bed_reader/tests/data/smallmodebad.bed
bed_reader/tests/data/small_no_fam.bed
bed_reader/tests/data/empty.bed
bed_reader/tests/data/sparse.bim
bed_reader/tests/data/small.bed
bed_reader/tests/data/small_no_bim.fam
bed_reader/tests/data/sparse.bed
bed_reader/tests/data/plink_sim_10s_100v_10pmiss.bed
bed_reader/tests/data/some_missing.bim
bed_reader/tests/data/plink_sim_10s_100v_10pmiss.bim
bed_reader/tests/data/smallmode0.bed
bed_reader/tests/data/small_no_bim.bed
bed_reader/tests/data/small_array.memmap
bed_reader/tests/data/some_missing.fam
bed_reader/tests/data/toydata.5chrom.bed
bed_reader/tests/data/some_missing.properties.npz
bed_reader/tests/test_open_bed.py
bed_reader/tests/benchmark/benchmark.py
bed_reader/tests/benchmark/bench2.ipynb
bed_reader/tests/__init__.py
bed_reader/tests/test_file_dot.py
bed_reader/tests/test_open_bed_cloud.py
bed_reader/__init__.py
bed_reader/_to_bed.py
bed_reader/_open_bed.py
bed_reader/_sample_data.py
bed_reader/bed_reader.cpython-313-aarch64-linux-gnu.so
bed_reader-1.0.6.dist-info/RECORD
