Metadata-Version: 2.3
Name: bed-reader
Version: 1.0.6
Classifier: Programming Language :: Python
Classifier: Programming Language :: Python :: 3.10
Classifier: Programming Language :: Python :: 3.11
Classifier: Programming Language :: Python :: 3.12
Classifier: Programming Language :: Python :: 3.13
Requires-Dist: numpy >=1.13.3
Requires-Dist: pooch >=1.5.0 ; extra == 'samples'
Requires-Dist: scipy >=1.4 ; extra == 'sparse'
Requires-Dist: pytest ; extra == 'dev'
Requires-Dist: pytest-cov ; extra == 'dev'
Requires-Dist: pytest-doctestplus ; extra == 'dev'
Requires-Dist: pytest-datadir ; extra == 'dev'
Requires-Dist: limix-sphinx-theme >=0.0.4 ; extra == 'dev'
Requires-Dist: pytest-sphinx >=0.2.2 ; extra == 'dev'
Requires-Dist: sphinx >=6.2.1 ; extra == 'dev'
Requires-Dist: sphinx-autoapi >=3.0.0 ; extra == 'dev'
Requires-Dist: maturin >=1.5.0 ; extra == 'dev'
Requires-Dist: pandas >=0.25.1 ; extra == 'dev'
Requires-Dist: recommonmark >=0.7.1 ; extra == 'dev'
Requires-Dist: ruff >=0.1.0 ; extra == 'dev'
Requires-Dist: numpy >=1.13.3 ; extra == 'min_dev'
Requires-Dist: pytest ; extra == 'min_dev'
Requires-Dist: pytest-datadir ; extra == 'min_dev'
Provides-Extra: samples
Provides-Extra: sparse
Provides-Extra: dev
Provides-Extra: min_dev
License-File: LICENSE.md
License-File: AUTHORS.txt
Summary: Read and write the PLINK BED format, simply and efficiently.
Keywords: bioinformatics,plink,genomics,genotype,snps
Home-Page: https://fastlmm.github.io/
Author: FaST-LMM Team <fastlmm-dev@python.org>
Author-email: FaST-LMM Team <fastlmm-dev@python.org>
License: Apache-2.0
Project-URL: homepage, https://fastlmm.github.io
Project-URL: source, https://github.com/fastlmm/bed-reader
Project-URL: bug-tracker, https://github.com/fastlmm/bed-reader/issues
Project-URL: documentation, http://fastlmm.github.io/bed-reader
